datasets/__init__.py
datasets/datasets.py
datasets/datasets_config.py
datasets_lib/__init__.py
datasets_lib/datasets.py
datasets_lib/datasets_config.py
datasets_lib-1.2.3.dist-info/DESCRIPTION.rst
datasets_lib-1.2.3.dist-info/METADATA
datasets_lib-1.2.3.dist-info/RECORD
datasets_lib-1.2.3.dist-info/WHEEL
datasets_lib-1.2.3.dist-info/metadata.json
datasets_lib-1.2.3.dist-info/top_level.txt
