Metadata-Version: 2.0
Name: datasets-lib
Version: 1.2.3
Summary: datasets library
Home-page: https://github.com/datasets-org/datasets-lib
Author: Vit Listik
Author-email: tivvit@seznam.cz
License: MIT
Keywords: datasets
Platform: UNKNOWN
Classifier: Development Status :: 5 - Production/Stable
Classifier: Intended Audience :: Developers
Classifier: Topic :: Software Development :: Libraries
Classifier: License :: OSI Approved :: MIT License
Classifier: Programming Language :: Python :: 2
Classifier: Programming Language :: Python :: 2.7
Classifier: Programming Language :: Python :: 3
Classifier: Programming Language :: Python :: 3.2
Classifier: Programming Language :: Python :: 3.3
Classifier: Programming Language :: Python :: 3.4
Classifier: Programming Language :: Python :: 3.5
Classifier: Programming Language :: Python :: 3.6
Classifier: Programming Language :: Python :: Implementation :: PyPy
Requires-Dist: confobj
Requires-Dist: typing
Requires-Dist: urljoin
